plumage/__init__.py
plumage/config.py
plumage/dom_transforms.py
plumage/favicon.py
plumage/package-lock.json
plumage/package.json
plumage/postcss.config.js
plumage/py.typed
plumage/static/css/code.scss
plumage/static/css/main.scss
plumage/static/css/mglass.scss
plumage/static/css/pygments/abap.css
plumage/static/css/pygments/algol.css
plumage/static/css/pygments/algol_nu.css
plumage/static/css/pygments/arduino.css
plumage/static/css/pygments/autumn.css
plumage/static/css/pygments/borland.css
plumage/static/css/pygments/bw.css
plumage/static/css/pygments/colorful.css
plumage/static/css/pygments/default.css
plumage/static/css/pygments/emacs.css
plumage/static/css/pygments/friendly.css
plumage/static/css/pygments/fruity.css
plumage/static/css/pygments/igor.css
plumage/static/css/pygments/inkpot.css
plumage/static/css/pygments/lovelace.css
plumage/static/css/pygments/manni.css
plumage/static/css/pygments/monokai.css
plumage/static/css/pygments/murphy.css
plumage/static/css/pygments/native.css
plumage/static/css/pygments/paraiso-dark.css
plumage/static/css/pygments/paraiso-light.css
plumage/static/css/pygments/pastie.css
plumage/static/css/pygments/perldoc.css
plumage/static/css/pygments/rainbow_dash.css
plumage/static/css/pygments/rrt.css
plumage/static/css/pygments/sas.css
plumage/static/css/pygments/solarized-dark.css
plumage/static/css/pygments/solarized-light.css
plumage/static/css/pygments/stata-dark.css
plumage/static/css/pygments/stata-light.css
plumage/static/css/pygments/stata.css
plumage/static/css/pygments/tango.css
plumage/static/css/pygments/trac.css
plumage/static/css/pygments/vim.css
plumage/static/css/pygments/vs.css
plumage/static/css/pygments/xcode.css
plumage/static/favicon/android-chrome-192x192.png
plumage/static/favicon/android-chrome-512x512.png
plumage/static/favicon/apple-touch-icon.png
plumage/static/favicon/browserconfig.xml
plumage/static/favicon/favicon-16x16.png
plumage/static/favicon/favicon-32x32.png
plumage/static/favicon/favicon.ico
plumage-4.0.0.dist-info/METADATA
plumage-4.0.0.dist-info/WHEEL
plumage-4.0.0.dist-info/RECORD
