Metadata-Version: 2.1
Name: plumage
Version: 4.0.0
Summary: Clean and tidy theme for Pelican.
Home-page: https://github.com/kdeldycke/plumage
License: GPL-2.0-or-later
Keywords: pelican,pelican-theme,stork,static-search,masonry,myst,theme,bootstrap,jquery
Author: Kevin Deldycke
Author-email: kevin@deldycke.com
Requires-Python: >=3.9,<4.0
Classifier: Development Status :: 5 - Production/Stable
Classifier: Environment :: Plugins
Classifier: Environment :: Web Environment
Classifier: Framework :: Pelican :: Themes
Classifier: Intended Audience :: Developers
Classifier: Intended Audience :: Information Technology
Classifier: License :: OSI Approved :: GNU General Public License v2 or later (GPLv2+)
Classifier: Operating System :: OS Independent
Classifier: Programming Language :: JavaScript
Classifier: Programming Language :: Other
Classifier: Programming Language :: Python :: 3
Classifier: Programming Language :: Python :: 3.9
Classifier: Programming Language :: Python :: 3.10
Classifier: Programming Language :: Python :: 3.11
Classifier: Programming Language :: Python :: 3.12
Classifier: Topic :: Internet :: WWW/HTTP
Classifier: Topic :: Internet :: WWW/HTTP :: Indexing/Search
Classifier: Topic :: Text Processing :: Markup :: HTML
Classifier: Topic :: Text Processing :: Markup :: Markdown
Classifier: Typing :: Typed
Requires-Dist: closure (>=20191111,<20191112)
Requires-Dist: cssmin (>=0.2.0,<0.3.0)
Requires-Dist: libsass (>=0.23.0,<0.24.0)
Requires-Dist: pelican (>=4.8.0,<5.0.0)
Requires-Dist: pelican-myst-reader (>=1.3.0b1,<2.0.0)
Requires-Dist: pelican-webassets (>=2.0.0,<3.0.0)
Requires-Dist: pynpm (>=0.2.0,<0.3.0)
Requires-Dist: pyquery (>=2.0.0,<3.0.0)
Project-URL: Changelog, https://github.com/kdeldycke/plumage/blob/main/changelog.md#changelog
Project-URL: Documentation, https://github.com/kdeldycke/plumage#settings
Project-URL: Funding, https://github.com/sponsors/kdeldycke
Project-URL: Issues, https://github.com/kdeldycke/plumage/issues
Project-URL: Repository, https://github.com/kdeldycke/plumage
